traffic_light_controller.v
`timescale 1ns/1ps

module traffic_light_controller (
    input clk,
    input reset,

    output reg ns_green,
    output reg ns_yellow,
    output reg ns_red,
    output reg ew_green,
    output reg ew_yellow,
    output reg ew_red
);

    //Parameters
    parameter NS_GREEN = 2'b00;
    parameter NS_YELLOW = 2'b01;
    parameter EW_GREEN = 2'b10;
    parameter EW_YELLOW = 2'b11;

    parameter GREEN_TIME = 10;
    parameter YELLOW_TIME = 3;

    //Registers
    reg [1:0] state;
    reg [1:0] next_state;

    reg [3:0] counter;
    reg timer_done;


    //STATE REGISTER
    always @(posedge clk or posedge reset) begin
        if(reset)
            state <= NS_GREEN;
        else
            state <= next_state;
    end
    

    //COUNTER BLOCK
    always@ (posedge clk or posedge reset) begin
        if(reset) begin
            counter <= 0;
            timer_done <= 0;
        end

        else begin
            
            timer_done <= 1'b0;

            case(state)

                NS_GREEN: begin
                    if(counter == GREEN_TIME - 1) begin
                        timer_done <= 1'b1;
                        counter <= 0;
                    end
                    else
                        counter <= counter + 1;
                end

                NS_YELLOW: begin
                    if(counter == YELLOW_TIME - 1) begin
                        timer_done <= 1'b1;
                        counter <= 0;
                    end
                    else
                        counter <= counter + 1;
                end

                EW_GREEN: begin
                    if(counter == GREEN_TIME - 1) begin
                        timer_done <= 1'b1;
                        counter <= 0;
                    end
                    else
                        counter <= counter + 1;
                end

                EW_YELLOW: begin
                    if(counter == YELLOW_TIME - 1) begin
                        timer_done <= 1'b1;
                        counter <= 0;
                    end
                    else
                        counter <= counter + 1;
                end

                default: begin
                    counter <= 0;
                    timer_done <= 1'b0;
                end
            endcase
        end
    end


    //NEXT STATE LOGIC
    always@ (*) begin
        
        //Default
        next_state = state;

        case (state)
            
            NS_GREEN:
            begin
                if(timer_done)
                    next_state = NS_YELLOW; 
            end 

            NS_YELLOW:
            begin
                if(timer_done)
                    next_state = EW_GREEN; 
            end

            EW_GREEN:
            begin
                if(timer_done)
                    next_state = EW_YELLOW; 
            end

            EW_YELLOW:
            begin
                if(timer_done)
                    next_state = NS_GREEN; 
            end

            default: 
                next_state = NS_GREEN;
        endcase
    end



    //OUTPUT LOGIC
    always @(*) begin

        ns_green = 1'b0;
        ns_yellow = 1'b0;
        ns_red = 1'b0;
        ew_green = 1'b0;
        ew_yellow = 1'b0;
        ew_red = 1'b0;

        case(state)

            NS_GREEN: begin
                ns_green = 1'b1;
                ew_red = 1'b1;
            end

            NS_YELLOW: begin
                ns_yellow = 1'b1;
                ew_red = 1'b1;
            end

            EW_GREEN: begin
                ns_red = 1'b1;
                ew_green = 1'b1;
            end

            EW_YELLOW: begin
                ns_red = 1'b1;
                ew_yellow = 1'b1;
            end

        endcase
    end


endmodule

tb_traffic_light_controller.v
`timescale 1ns/1ps

module tb_traffic_light_controller;

reg clk;
reg reset;

wire ns_green;
wire ns_yellow;
wire ns_red;
wire ew_green;
wire ew_yellow;
wire ew_red;


traffic_light_controller dut(
    .clk(clk),
    .reset(reset),
    .ns_green(ns_green),
    .ns_yellow(ns_yellow),
    .ns_red(ns_red),
    .ew_green(ew_green),
    .ew_yellow(ew_yellow),
    .ew_red(ew_red)
);


always #5 clk = ~clk;

initial begin
    
    $monitor("Time = %0t | Clk = %b | Reset = %b | ns_green = %b | ns_yellow = %b | ns_red = %b | ew_green = %b | ew_yellow = %b | ew_red = %b", $time, clk, reset, ns_green, ns_yellow, ns_red, ew_green, ew_yellow, ew_red);

end

initial begin
    
    $dumpfile("traffic_light_controller.vcd");
    $dumpvars(0, tb_traffic_light_controller);

    clk = 0;
    reset = 1;

    #10;
    reset = 0;

    #200;

    $finish;

end
    
endmodule

traffic_light_controller.vcd
$date
	Thu Aug 20 11:29:35 2026
$end
$version
	Icarus Verilog
$end
$timescale
	1ps
$end
$scope module tb_traffic_light_controller $end
$var wire 1 ! ns_yellow $end
$var wire 1 " ns_red $end
$var wire 1 # ns_green $end
$var wire 1 $ ew_yellow $end
$var wire 1 % ew_red $end
$var wire 1 & ew_green $end
$var reg 1 ' clk $end
$var reg 1 ( reset $end
$scope module dut $end
$var wire 1 ' clk $end
$var wire 1 ( reset $end
$var reg 4 ) counter [3:0] $end
$var reg 1 & ew_green $end
$var reg 1 % ew_red $end
$var reg 1 $ ew_yellow $end
$var reg 2 * next_state [1:0] $end
$var reg 1 # ns_green $end
$var reg 1 " ns_red $end
$var reg 1 ! ns_yellow $end
$var reg 2 + state [1:0] $end
$var reg 1 , timer_done $end
$upscope $end
$upscope $end
$enddefinitions $end
#0
$dumpvars
0,
b0 +
b0 *
b0 )
1(
0'
0&
1%
0$
1#
0"
0!
$end
#5000
1'
#10000
0'
0(
#15000
b1 )
1'
#20000
0'
#25000
b10 )
1'
#30000
0'
#35000
b11 )
1'
#40000
0'
#45000
b100 )
1'
#50000
0'
#55000
b101 )
1'
#60000
0'
#65000
b110 )
1'
#70000
0'
#75000
b111 )
1'
#80000
0'
#85000
b1000 )
1'
#90000
0'
#95000
b1001 )
1'
#100000
0'
#105000
b1 *
b0 )
1,
1'
#110000
0'
#115000
1!
1%
0#
b1 +
b1 )
0,
1'
#120000
0'
#125000
b10 )
1'
#130000
0'
#135000
b10 *
b0 )
1,
1'
#140000
0'
#145000
1&
1"
0%
0!
b1 )
0,
b10 +
1'
#150000
0'
#155000
b10 )
1'
#160000
0'
#165000
b11 )
1'
#170000
0'
#175000
b100 )
1'
#180000
0'
#185000
b101 )
1'
#190000
0'
#195000
b110 )
1'
#200000
0'
#205000
b111 )
1'
